sphinx_exercise/__init__.py
sphinx_exercise/_compat.py
sphinx_exercise/directive.py
sphinx_exercise/latex.py
sphinx_exercise/nodes.py
sphinx_exercise/post_transforms.py
sphinx_exercise/transforms.py
sphinx_exercise/utils.py
sphinx_exercise/assets/html/exercise.css
sphinx_exercise/translations/README.md
sphinx_exercise/translations/_convert.py
sphinx_exercise/translations/jsons/Exercise.json
sphinx_exercise/translations/jsons/Solution.json
sphinx_exercise/translations/locales/ar/LC_MESSAGES/exercise.mo
sphinx_exercise/translations/locales/ar/LC_MESSAGES/exercise.po
sphinx_exercise/translations/locales/bn/LC_MESSAGES/exercise.mo
sphinx_exercise/translations/locales/bn/LC_MESSAGES/exercise.po
sphinx_exercise/translations/locales/cs/LC_MESSAGES/exercise.mo
sphinx_exercise/translations/locales/cs/LC_MESSAGES/exercise.po
sphinx_exercise/translations/locales/de/LC_MESSAGES/exercise.mo
sphinx_exercise/translations/locales/de/LC_MESSAGES/exercise.po
sphinx_exercise/translations/locales/el/LC_MESSAGES/exercise.mo
sphinx_exercise/translations/locales/el/LC_MESSAGES/exercise.po
sphinx_exercise/translations/locales/es/LC_MESSAGES/exercise.mo
sphinx_exercise/translations/locales/es/LC_MESSAGES/exercise.po
sphinx_exercise/translations/locales/fr/LC_MESSAGES/exercise.mo
sphinx_exercise/translations/locales/fr/LC_MESSAGES/exercise.po
sphinx_exercise/translations/locales/hi/LC_MESSAGES/exercise.mo
sphinx_exercise/translations/locales/hi/LC_MESSAGES/exercise.po
sphinx_exercise/translations/locales/hu/LC_MESSAGES/exercise.mo
sphinx_exercise/translations/locales/hu/LC_MESSAGES/exercise.po
sphinx_exercise/translations/locales/id/LC_MESSAGES/exercise.mo
sphinx_exercise/translations/locales/id/LC_MESSAGES/exercise.po
sphinx_exercise/translations/locales/it/LC_MESSAGES/exercise.mo
sphinx_exercise/translations/locales/it/LC_MESSAGES/exercise.po
sphinx_exercise/translations/locales/ja/LC_MESSAGES/exercise.mo
sphinx_exercise/translations/locales/ja/LC_MESSAGES/exercise.po
sphinx_exercise-1.2.1.dist-info/METADATA
sphinx_exercise-1.2.1.dist-info/WHEEL
sphinx_exercise-1.2.1.dist-info/licenses/LICENSE
sphinx_exercise-1.2.1.dist-info/RECORD
