Metadata-Version: 2.4
Name: sphinx-exercise
Version: 1.2.1
Summary: A Sphinx extension for producing exercises and solutions.
Project-URL: Homepage, https://github.com/executablebooks/sphinx-exercise
Project-URL: Source, https://github.com/executablebooks/sphinx-exercise
Project-URL: Tracker, https://github.com/executablebooks/sphinx-exercise/issues
Author-email: QuantEcon <admin@quantecon.org>
License: MIT License
License-File: LICENSE
Classifier: Development Status :: 4 - Beta
Classifier: Environment :: Plugins
Classifier: Environment :: Web Environment
Classifier: Framework :: Sphinx :: Extension
Classifier: Intended Audience :: Developers
Classifier: License :: OSI Approved :: MIT License
Classifier: Natural Language :: English
Classifier: Operating System :: OS Independent
Classifier: Programming Language :: Python
Classifier: Programming Language :: Python :: 3.10
Classifier: Programming Language :: Python :: 3.11
Classifier: Programming Language :: Python :: 3.12
Classifier: Programming Language :: Python :: 3.13
Classifier: Topic :: Documentation
Classifier: Topic :: Documentation :: Sphinx
Classifier: Topic :: Software Development :: Documentation
Classifier: Topic :: Text Processing
Classifier: Topic :: Utilities
Requires-Python: >=3.10
Requires-Dist: sphinx-book-theme
Requires-Dist: sphinx>=6.1
Provides-Extra: all
Requires-Dist: beautifulsoup4; extra == 'all'
Requires-Dist: black; extra == 'all'
Requires-Dist: coverage; extra == 'all'
Requires-Dist: defusedxml; extra == 'all'
Requires-Dist: flake8<3.8.0,>=3.7.0; extra == 'all'
Requires-Dist: matplotlib>=3.8; extra == 'all'
Requires-Dist: myst-nb>=1.1.0; extra == 'all'
Requires-Dist: pre-commit; extra == 'all'
Requires-Dist: pytest-cov; extra == 'all'
Requires-Dist: pytest-regressions; extra == 'all'
Requires-Dist: pytest>=8.0; extra == 'all'
Requires-Dist: sphinx-book-theme; extra == 'all'
Requires-Dist: sphinx-togglebutton; extra == 'all'
Requires-Dist: sphinx<9,>=6.1; extra == 'all'
Requires-Dist: texsoup; extra == 'all'
Provides-Extra: code-style
Requires-Dist: black; extra == 'code-style'
Requires-Dist: flake8<3.8.0,>=3.7.0; extra == 'code-style'
Requires-Dist: pre-commit; extra == 'code-style'
Provides-Extra: rtd
Requires-Dist: myst-nb>=1.1.0; extra == 'rtd'
Requires-Dist: sphinx-book-theme; extra == 'rtd'
Requires-Dist: sphinx-togglebutton; extra == 'rtd'
Requires-Dist: sphinx<9,>=6.1; extra == 'rtd'
Provides-Extra: testing
Requires-Dist: beautifulsoup4; extra == 'testing'
Requires-Dist: coverage; extra == 'testing'
Requires-Dist: defusedxml; extra == 'testing'
Requires-Dist: matplotlib>=3.8; extra == 'testing'
Requires-Dist: myst-nb>=1.1.0; extra == 'testing'
Requires-Dist: pytest-cov; extra == 'testing'
Requires-Dist: pytest-regressions; extra == 'testing'
Requires-Dist: pytest>=8.0; extra == 'testing'
Requires-Dist: sphinx<9,>=6.1; extra == 'testing'
Requires-Dist: texsoup; extra == 'testing'
